edit_anki-0.1.2.dist-info/METADATA
edit_anki-0.1.2.dist-info/WHEEL
edit_anki-0.1.2.dist-info/license_files/LICENSE
edit_anki/__init__.py
edit_anki/__init__.pyi
edit_anki/py.typed
edit_anki/edit_anki.abi3.so
edit_anki-0.1.2.dist-info/RECORD
